dependency_checker/__init__.py
dependency_checker/_nbdev.py
dependency_checker/checker.py
dependency_checker/pipreqs.py
dependency_checker-0.0.5.dist-info/LICENSE
dependency_checker-0.0.5.dist-info/METADATA
dependency_checker-0.0.5.dist-info/WHEEL
dependency_checker-0.0.5.dist-info/entry_points.txt
dependency_checker-0.0.5.dist-info/top_level.txt
dependency_checker-0.0.5.dist-info/RECORD
