Metadata-Version: 2.1
Name: dependency-checker
Version: 0.0.5
Summary: A lightweight pythonic way to check if a package's dependencies are out of date
Home-page: https://github.com/muellerzr/dependency_checker/tree/master/
Author: Zachary Mueller
Author-email: muellerzr@gmail.com
License: Apache Software License 2.0
Keywords: pipdeptree pypi dependency
Platform: UNKNOWN
Classifier: Development Status :: 3 - Alpha
Classifier: Intended Audience :: Developers
Classifier: Natural Language :: English
Classifier: Programming Language :: Python :: 3.7
Classifier: Programming Language :: Python :: 3.8
Classifier: License :: OSI Approved :: Apache Software License
Requires-Python: >=3.7
License-File: LICENSE
Requires-Dist: pip
Requires-Dist: packaging
Requires-Dist: pipdeptree (>=2.2.1)
Requires-Dist: pipreqs (>=0.4.11)
Requires-Dist: PyGithub
Provides-Extra: dev
